mmdeploy_runtime/__init__.py
mmdeploy_runtime/_win_dll_path.py
mmdeploy_runtime/mmdeploy.dll
mmdeploy_runtime/mmdeploy_ort_net.dll
mmdeploy_runtime/mmdeploy_runtime.cp38-win_amd64.pyd
mmdeploy_runtime/mmdeploy_trt_net.dll
mmdeploy_runtime/onnxruntime.dll
mmdeploy_runtime/version.py
mmdeploy_runtime_gpu-1.3.1.dist-info/METADATA
mmdeploy_runtime_gpu-1.3.1.dist-info/WHEEL
mmdeploy_runtime_gpu-1.3.1.dist-info/top_level.txt
mmdeploy_runtime_gpu-1.3.1.dist-info/RECORD
