Metadata-Version: 2.1
Name: mmdeploy-runtime-gpu
Version: 1.3.1
Summary: OpenMMLab Model Deployment SDK python api
Home-page: https://github.com/open-mmlab/mmdeploy
Author: OpenMMLab
Author-email: openmmlab@gmail.com
License: Apache License 2.0
Keywords: computer vision,model deployment
Platform: x86_64
